unixv4_tape_validator/__init__.py
unixv4_tape_validator/main.py
unixv4_tape_validator/prompts.py
unixv4_tape_validator-2025.12.21111300.dist-info/METADATA
unixv4_tape_validator-2025.12.21111300.dist-info/WHEEL
unixv4_tape_validator-2025.12.21111300.dist-info/top_level.txt
unixv4_tape_validator-2025.12.21111300.dist-info/RECORD
