Metadata-Version: 2.4
Name: unixv4-tape-validator
Version: 2025.12.21111300
Summary: A new package is designed to interpret and confirm the successful archival of Unix V4 tapes by processing user-provided text inputs. It extracts structured information indicating success or failure an
Author-email: unixv4-tape-validator <hi@eugene.plus>
License: MIT
Project-URL: Homepage, https://github.com/chigwell/unixv4-tape-validator
Requires-Python: >=3.9
Requires-Dist: langchain-llm7>=0.0.0
Requires-Dist: llmatch-messages>=0.0.0
Requires-Dist: langchain-core>=0.3.0
